akeyra/__init__.py
akeyra/akeyra.py
akeyra-0.1.2.dist-info/METADATA
akeyra-0.1.2.dist-info/RECORD
akeyra-0.1.2.dist-info/WHEEL
akeyra-0.1.2.dist-info/entry_points.txt
akeyra-0.1.2.dist-info/top_level.txt
