Metadata-Version: 2.1
Name: akeyra
Version: 0.1.2
Summary: Client app for Sakeyra
Home-page: https://github.com/LaMethode/akeyra
Author: Jeremy Collin
Author-email: jeremy.collin.lnk@gmail.com
License: GPLv3
Platform: UNKNOWN
Classifier: Programming Language :: Python
Classifier: Development Status :: 4 - Beta
Classifier: Environment :: Console
Classifier: Natural Language :: French
Classifier: Operating System :: POSIX :: Linux
Classifier: Programming Language :: Python :: 3.5
Classifier: Intended Audience :: System Administrators
Classifier: License :: OSI Approved :: GNU General Public License v3 or later (GPLv3+)
Classifier: Topic :: System :: Systems Administration
Requires-Dist: configparser (==3.5.0)
Requires-Dist: pyjwt (==1.5.3)
Requires-Dist: requests (==2.18.4)
